Workbook

Sheet Dashboard
A1: STUDENT BUDGET DASHBOARD - 2025
A3: Total Income | C3: Total Expense | E3: Net Savings | G3: Avg Savings Rate
A4: ='Monthly Summary'!C14 | C4: ='Monthly Summary'!D14 | E4: ='Monthly Summary'!E14 | G4: ='Monthly Summary'!F14

Sheet Transactions
A1: Date | B1: Type | C1: Category | D1: Description | E1: Amount | F1: Payment Mode | G1: Month | H1: Month Name
A2: 45993 | B2: Expense | C2: Entertainment | D2: Event Ticket | E2: 549.54 | F2: UPI | G2: =MONTH(A2) | H2: =TEXT(A2,"mmm")
A3: 45970 | B3: Expense | C3: Food & Snacks | D3: Canteen | E3: 126.02 | F3: UPI | G3: =MONTH(A3) | H3: =TEXT(A3,"mmm")
A4: 45907 | B4: Expense | C4: Entertainment | D4: Movie Ticket | E4: 175.44 | F4: Cash | G4: =MONTH(A4) | H4: =TEXT(A4,"mmm")
A5: 45756 | B5: Expense | C5: Entertainment | D5: Movie Ticket | E5: 344.18 | F5: UPI | G5: =MONTH(A5) | H5: =TEXT(A5,"mmm")
A6: 46010 | B6: Expense | C6: Savings | D6: Transfer to Savings Account | E6: 640.73 | F6: Cash | G6: =MONTH(A6) | H6: =TEXT(A6,"mmm")
A7: 45805 | B7: Expense | C7: Food & Snacks | D7: Restaurant | E7: 71.94 | F7: Net Banking | G7: =MONTH(A7) | H7: =TEXT(A7,"mmm")
A8: 45989 | B8: Expense | C8: Education | D8: Stationery | E8: 788.39 | F8: UPI | G8: =MONTH(A8) | H8: =TEXT(A8,"mmm")
A9: 45665 | B9: Expense | C9: Food & Snacks | D9: Tea/Snacks | E9: 126.19 | F9: Cash | G9: =MONTH(A9) | H9: =TEXT(A9,"mmm")
A10: 45967 | B10: Expense | C10: Subscriptions | D10: Netflix/OTT Share | E10: 274.56 | F10: Cash | G10: =MONTH(A10) | H10: =TEXT(A10,"mmm")
A11: 45674 | B11: Expense | C11: Food & Snacks | D11: Grocery | E11: 90.97 | F11: Cash | G11: =MONTH(A11) | H11: =TEXT(A11,"mmm")
A12: 46003 | B12: Expense | C12: Subscriptions | D12: Spotify Premium | E12: 275.72 | F12: UPI | G12: =MONTH(A12) | H12: =TEXT(A12,"mmm")
A13: 45830 | B13: Expense | C13: Food & Snacks | D13: Tiffin | E13: 239.55 | F13: Cash | G13: =MONTH(A13) | H13: =TEXT(A13,"mmm")
... A444: 45759 | B444: Expense | C444: Food & Snacks | D444: Restaurant | E444: 146.4 | F444: Cash | G444: =MONTH(A444) | H444: =TEXT(A444,"mmm")

Sheet Budget
A1: Category | B1: Monthly Budget | C1: Annual Budget
A2: Food & Snacks | B2: 2500 | C2: =B2*12
A3: Transportation | B3: 600 | C3: =B3*12
A4: Mobile & Internet | B4: 350 | C4: =B4*12
A5: Education | B5: 400 | C5: =B5*12
A6: Entertainment | B6: 500 | C6: =B6*12
A7: Subscriptions | B7: 250 | C7: =B7*12
A8: Personal Care | B8: 200 | C8: =B8*12
A9: Clothing | B9: 400 | C9: =B9*12
A10: Savings | B10: 1500 | C10: =B10*12
A11: Miscellaneous | B11: 200 | C11: =B11*12
A12: Total | B12: =SUM(B2:B11) | C12: =SUM(C2:C11)

Sheet Monthly Summary
A1: Month | B1: Month # | C1: Income | D1: Expense | E1: Net Savings | F1: Savings Rate
A2: Jan | B2: 1 | C2: =SUMIFS(Transactions!E2:E444,Transactions!B2:B444,"Income",Transactions!G2:G444,B2) | D2: =SUMIFS(Transactions!E2:E444,Transactions!B2:B444,"Expense",Transactions!G2:G444,B2) | E2: =C2-D2 | F2: =IF(C2=0,0,E2/C2)
A3: Feb | B3: 2 | C3: =SUMIFS(Transactions!E2:E444,Transactions!B2:B444,"Income",Transactions!G2:G444,B3) | D3: =SUMIFS(Transactions!E2:E444,Transactions!B2:B444,"Expense",Transactions!G2:G444,B3) | E3: =C3-D3 | F3: =IF(C3=0,0,E3/C3)
A4: Mar | B4: 3 | C4: =SUMIFS(Transactions!E2:E444,Transactions!B2:B444,"Income",Transactions!G2:G444,B4) | D4: =SUMIFS(Transactions!E2:E444,Transactions!B2:B444,"Expense",Transactions!G2:G444,B4) | E4: =C4-D4 | F4: =IF(C4=0,0,E4/C4)
A5: Apr | B5: 4 | C5: =SUMIFS(Transactions!E2:E444,Transactions!B2:B444,"Income",Transactions!G2:G444,B5) | D5: =SUMIFS(Transactions!E2:E444,Transactions!B2:B444,"Expense",Transactions!G2:G444,B5) | E5: =C5-D5 | F5: =IF(C5=0,0,E5/C5)
A6: May | B6: 5 | C6: =SUMIFS(Transactions!E2:E444,Transactions!B2:B444,"Income",Transactions!G2:G444,B6) | D6: =SUMIFS(Transactions!E2:E444,Transactions!B2:B444,"Expense",Transactions!G2:G444,B6) | E6: =C6-D6 | F6: =IF(C6=0,0,E6/C6)
A7: Jun | B7: 6 | C7: =SUMIFS(Transactions!E2:E444,Transactions!B2:B444,"Income",Transactions!G2:G444,B7) | D7: =SUMIFS(Transactions!E2:E444,Transactions!B2:B444,"Expense",Transactions!G2:G444,B7) | E7: =C7-D7 | F7: =IF(C7=0,0,E7/C7)
A8: Jul | B8: 7 | C8: =SUMIFS(Transactions!E2:E444,Transactions!B2:B444,"Income",Transactions!G2:G444,B8) | D8: =SUMIFS(Transactions!E2:E444,Transactions!B2:B444,"Expense",Transactions!G2:G444,B8) | E8: =C8-D8 | F8: =IF(C8=0,0,E8/C8)
A9: Aug | B9: 8 | C9: =SUMIFS(Transactions!E2:E444,Transactions!B2:B444,"Income",Transactions!G2:G444,B9) | D9: =SUMIFS(Transactions!E2:E444,Transactions!B2:B444,"Expense",Transactions!G2:G444,B9) | E9: =C9-D9 | F9: =IF(C9=0,0,E9/C9)
A10: Sep | B10: 9 | C10: =SUMIFS(Transactions!E2:E444,Transactions!B2:B444,"Income",Transactions!G2:G444,B10) | D10: =SUMIFS(Transactions!E2:E444,Transactions!B2:B444,"Expense",Transactions!G2:G444,B10) | E10: =C10-D10 | F10: =IF(C10=0,0,E10/C10)
A11: Oct | B11: 10 | C11: =SUMIFS(Transactions!E2:E444,Transactions!B2:B444,"Income",Transactions!G2:G444,B11) | D11: =SUMIFS(Transactions!E2:E444,Transactions!B2:B444,"Expense",Transactions!G2:G444,B11) | E11: =C11-D11 | F11: =IF(C11=0,0,E11/C11)
A12: Nov | B12: 11 | C12: =SUMIFS(Transactions!E2:E444,Transactions!B2:B444,"Income",Transactions!G2:G444,B12) | D12: =SUMIFS(Transactions!E2:E444,Transactions!B2:B444,"Expense",Transactions!G2:G444,B12) | E12: =C12-D12 | F12: =IF(C12=0,0,E12/C12)
A13: Dec | B13: 12 | C13: =SUMIFS(Transactions!E2:E444,Transactions!B2:B444,"Income",Transactions!G2:G444,B13) | D13: =SUMIFS(Transactions!E2:E444,Transactions!B2:B444,"Expense",Transactions!G2:G444,B13) | E13: =C13-D13 | F13: =IF(C13=0,0,E13/C13)
A14: Total / Avg | C14: =SUM(C2:C13) | D14: =SUM(D2:D13) | E14: =SUM(E2:E13) | F14: =AVERAGE(F2:F13)

Sheet Budget vs Actual
A1: Category | B1: Annual Budget | C1: Actual Spent | D1: Variance | E1: % of Budget Used
A2: Food & Snacks | B2: =Budget!C2 | C2: =SUMIFS(Transactions!E2:E444,Transactions!B2:B444,"Expense",Transactions!C2:C444,A2) | D2: =B2-C2 | E2: =IF(B2=0,0,C2/B2)
A3: Transportation | B3: =Budget!C3 | C3: =SUMIFS(Transactions!E2:E444,Transactions!B2:B444,"Expense",Transactions!C2:C444,A3) | D3: =B3-C3 | E3: =IF(B3=0,0,C3/B3)
A4: Mobile & Internet | B4: =Budget!C4 | C4: =SUMIFS(Transactions!E2:E444,Transactions!B2:B444,"Expense",Transactions!C2:C444,A4) | D4: =B4-C4 | E4: =IF(B4=0,0,C4/B4)
A5: Education | B5: =Budget!C5 | C5: =SUMIFS(Transactions!E2:E444,Transactions!B2:B444,"Expense",Transactions!C2:C444,A5) | D5: =B5-C5 | E5: =IF(B5=0,0,C5/B5)
A6: Entertainment | B6: =Budget!C6 | C6: =SUMIFS(Transactions!E2:E444,Transactions!B2:B444,"Expense",Transactions!C2:C444,A6) | D6: =B6-C6 | E6: =IF(B6=0,0,C6/B6)
A7: Subscriptions | B7: =Budget!C7 | C7: =SUMIFS(Transactions!E2:E444,Transactions!B2:B444,"Expense",Transactions!C2:C444,A7) | D7: =B7-C7 | E7: =IF(B7=0,0,C7/B7)
A8: Personal Care | B8: =Budget!C8 | C8: =SUMIFS(Transactions!E2:E444,Transactions!B2:B444,"Expense",Transactions!C2:C444,A8) | D8: =B8-C8 | E8: =IF(B8=0,0,C8/B8)
A9: Clothing | B9: =Budget!C9 | C9: =SUMIFS(Transactions!E2:E444,Transactions!B2:B444,"Expense",Transactions!C2:C444,A9) | D9: =B9-C9 | E9: =IF(B9=0,0,C9/B9)
A10: Savings | B10: =Budget!C10 | C10: =SUMIFS(Transactions!E2:E444,Transactions!B2:B444,"Expense",Transactions!C2:C444,A10) | D10: =B10-C10 | E10: =IF(B10=0,0,C10/B10)
A11: Miscellaneous | B11: =Budget!C11 | C11: =SUMIFS(Transactions!E2:E444,Transactions!B2:B444,"Expense",Transactions!C2:C444,A11) | D11: =B11-C11 | E11: =IF(B11=0,0,C11/B11)
A12: Total | B12: =SUM(B2:B11) | C12: =SUM(C2:C11) | D12: =SUM(D2:D11) | E12: =IF(B12=0,0,C12/B12)
